5x_streamlit_session_manager-0.1.1.dist-info/licenses/LICENSE
streamlit_session_manager/__init__.py
streamlit_session_manager/session_manager.py
5x_streamlit_session_manager-0.1.1.dist-info/METADATA
5x_streamlit_session_manager-0.1.1.dist-info/WHEEL
5x_streamlit_session_manager-0.1.1.dist-info/top_level.txt
5x_streamlit_session_manager-0.1.1.dist-info/RECORD
