Metadata-Version: 2.4
Name: 5x-streamlit-session-manager
Version: 0.1.1
Summary: A library to fetch user session data from encrypted URL parameters in 5x Streamlit apps
Home-page: https://github.com/5X-nextgen-customer-repo-prod/streamlit_session_manager.gitc
Author: 5X
Author-email: support@5x.co
License: MIT
Classifier: Programming Language :: Python :: 3.8
Classifier: Programming Language :: Python :: 3.9
Classifier: Programming Language :: Python :: 3.10
Classifier: Programming Language :: Python :: 3.11
Classifier: Programming Language :: Python :: 3.12
Classifier: License :: OSI Approved :: MIT License
Classifier: Operating System :: OS Independent
Classifier: Development Status :: 3 - Alpha
Classifier: Intended Audience :: Developers
Classifier: Topic :: Software Development :: Libraries :: Python Modules
Requires-Python: >=3.8
License-File: LICENSE
Requires-Dist: extra-streamlit-components
Requires-Dist: cryptography>=36.0.0
Dynamic: author
Dynamic: author-email
Dynamic: classifier
Dynamic: description
Dynamic: description-content-type
Dynamic: home-page
Dynamic: license
Dynamic: license-file
Dynamic: requires-dist
Dynamic: requires-python
Dynamic: summary
